gym_envs/__init__.py
gym_envs/env_kwargs.py
gym_envs/export_env_list.py
gym_envs/widowx_env/__init__.py
gym_envs/widowx_env/env_description.py
gym_envs/widowx_env/widowx_env.py
gym_envs-2.2.2.dist-info/LICENSE
gym_envs-2.2.2.dist-info/METADATA
gym_envs-2.2.2.dist-info/WHEEL
gym_envs-2.2.2.dist-info/top_level.txt
gym_envs-2.2.2.dist-info/RECORD
