Metadata-Version: 2.1
Name: gym-envs
Version: 2.2.2
Summary: Gym environments for RL reaching tasks
Home-page: https://github.com/pypa/sampleproject
Download-URL: https://pypi.org/project/elastictools/
Author: sanjeev
License: MIT
Keywords: Reinforcement_Learning,OpenAI_Gym
Classifier: Programming Language :: Python :: 3
Classifier: License :: OSI Approved :: MIT License
Classifier: Operating System :: OS Independent
Requires-Python: >=3.6
License-File: LICENSE
Requires-Dist: gym
Requires-Dist: numpy
Requires-Dist: pybullet
